AutoDock/__init__.py
AutoDock/config.py
AutoDock/providers_test.py
AutoDock/utilities.py
auto_dock_2024-0.8.0.dist-info/METADATA
auto_dock_2024-0.8.0.dist-info/WHEEL
auto_dock_2024-0.8.0.dist-info/RECORD
