Metadata-Version: 2.1
Name: auto_dock_2024
Version: 0.8.0
Summary: This code can make documentation for your project
Author: dima-on
Author-email: sinica911@gmail.com
Requires-Python: >=3.12,<4.0
Classifier: Programming Language :: Python :: 3
Classifier: Programming Language :: Python :: 3.12
Classifier: Programming Language :: Python :: 3.13
